windows_filepath/LICENSE
windows_filepath/README.MD
windows_filepath/__init__.py
windows_filepath/requirements.txt
windows_filepath/thirdparty.json
windows_filepath-0.10.dist-info/LICENSE.rst
windows_filepath-0.10.dist-info/METADATA
windows_filepath-0.10.dist-info/WHEEL
windows_filepath-0.10.dist-info/top_level.txt
windows_filepath-0.10.dist-info/RECORD
